transforms/__init__.py
transforms/code.py
transforms/data_manager.py
transforms/generate_types.py
transforms/manage.py
transforms/run.py
transforms/start_connect_server.py
transforms/types.py
transforms/api/__init__.py
transforms/api/check.py
transforms/api/configure.py
transforms/api/incremental_transform.py
transforms/api/pipeline.py
transforms/api/transform_df.py
transforms/api/tests/__init__.py
transforms/api/tests/test_discovery.py
transforms/api/tests/test_transform_df.py
transforms/api/tests/example_module/__init__.py
transforms/api/tests/example_module/transform1.py
transforms/api/tests/example_module/transform2.py
transforms/api/tests/example_module/example_subdir/__init__.py
transforms/api/tests/example_module/example_subdir/transform3.py
transforms/engine/duckdb.py
transforms/engine/spark.py
transforms/engine/spark_sail.py
transforms/examples/simple_transform.py
transforms/expectations/__init__.py
transforms/expectations/base.py
transforms/expectations/colexpects.py
transforms/expectations/conditional_expectations.py
transforms/expectations/count_expectations.py
transforms/expectations/grouped.py
transforms/external/__init__.py
transforms/external/systems.py
transforms/runner/default_executor.py
transforms/runner/exec_check.py
transforms/runner/exec_transform.py
transforms/runner/data_sink/base.py
transforms/runner/data_sink/local_file_sink.py
transforms/runner/data_sink/local_file_sink_with_duck.py
transforms/runner/data_source/base.py
transforms/runner/data_source/foundry_source.py
transforms/runner/data_source/foundry_source_with_duck.py
transforms/runner/data_source/local_file_source.py
transforms/runner/data_source/mixed_source.py
transforms/runner/patches/rdd.py
transforms/runner/patches/test_patch_rdd.py
transforms/tests/test_dataset_collection.py
transforms/tests/test_expectations.py
transforms/tests/test_generation.py
transforms/tests/test_transform.py
transforms/tests/test_datasets/iris/spark/iris.parquet
foundry_duck_transforms-0.1.4.dist-info/METADATA
foundry_duck_transforms-0.1.4.dist-info/WHEEL
foundry_duck_transforms-0.1.4.dist-info/licenses/LICENSE
foundry_duck_transforms-0.1.4.dist-info/RECORD
