Metadata-Version: 2.4
Name: foundry-duck-transforms
Version: 0.1.4
Summary: Run transforms quickly on local machine and analyse using DuckDb and pyspark
Author-email: Emil Redzik <kontakt@eredzik.com>
License: Apache-2.0
License-File: LICENSE
Classifier: Development Status :: 5 - Production/Stable
Classifier: Intended Audience :: Developers
Classifier: License :: OSI Approved :: Apache Software License
Classifier: Operating System :: MacOS
Classifier: Operating System :: Microsoft :: Windows
Classifier: Operating System :: POSIX :: Linux
Classifier: Programming Language :: Python
Classifier: Programming Language :: Python :: 3 :: Only
Classifier: Programming Language :: Python :: 3.10
Classifier: Programming Language :: Python :: 3.11
Classifier: Topic :: Scientific/Engineering :: Information Analysis
Requires-Python: >=3.10
Requires-Dist: asyncer
Requires-Dist: duckdb
Requires-Dist: foundry-dev-tools
Requires-Dist: pandas
Requires-Dist: pyarrow
Requires-Dist: pyspark
Requires-Dist: sqlframe
Requires-Dist: typer
Provides-Extra: dev
Requires-Dist: pyspark>=3.0.0; extra == 'dev'
